unifier/__init__.py
unifier/unifier.py
unifier-0.1.17.dist-info/licenses/LICENSE
unifier-0.1.17.dist-info/METADATA
unifier-0.1.17.dist-info/WHEEL
unifier-0.1.17.dist-info/top_level.txt
unifier-0.1.17.dist-info/RECORD
